rdcanon/__init__.py
rdcanon/askcos_prims.py
rdcanon/drugbank_prims_with_nots.py
rdcanon/main.py
rdcanon/np_prims.py
rdcanon/pubchem_prims.py
rdcanon/rdcanon_tests.py
rdcanon/rec_util.py
rdcanon/token_parser.py
rdcanon/util.py
rdcanon/manuscript/gen_plots_run_reactants_20240104.ipynb
rdcanon/manuscript/gen_retrosim_plots_20240105.ipynb
rdcanon/manuscript/generate_plots_substruct_match.ipynb
rdcanon/manuscript/prim_frequencies.ipynb
rdcanon/manuscript/data/coconut_simple_search_curcumin.sdf
rdcanon/manuscript/data/coconut_simple_search_quercetin.sdf
rdcanon/manuscript/data/drugbank_non_matching_substruct_dataset_20240108.xlsx
rdcanon/manuscript/data/npatlas_non_matching_substruct_dataset_20240108.xlsx
rdcanon/manuscript/data/pubchem_non_matching_substruct_dataset_20240108.xlsx
rdcanon/manuscript/data/reaction_smarts_out.xlsx
rdcanon/testing_data/drugbank_non_matching_substruct_dataset_20240108.xlsx
rdcanon/testing_data/drugbank_smiles_1000.xlsx
rdcanon/testing_data/noncanon_efg_templates_20240108.xlsx
rdcanon/testing_data/reaction_smarts_out.xlsx
rdcanon-0.1.2.dist-info/METADATA
rdcanon-0.1.2.dist-info/WHEEL
rdcanon-0.1.2.dist-info/licenses/LICENSE
rdcanon-0.1.2.dist-info/RECORD
