Metadata-Version: 2.4
Name: rdcanon
Version: 0.1.2
Summary: SMARTS Sanitization/Canonicalization
Project-URL: Homepage, https://github.com/coleygroup/rdcanon
Project-URL: Issues, https://github.com/coleygroup/rdcanon/issues
Author-email: Babak Mahjour <bmahjour@mit.edu>
License: MIT License
License-File: LICENSE
Classifier: Operating System :: OS Independent
Classifier: Programming Language :: Python :: 3
Requires-Python: >=3.8
Requires-Dist: ipykernel
Requires-Dist: lark
Requires-Dist: matplotlib
Requires-Dist: networkx
Requires-Dist: numpy
Requires-Dist: openpyxl
Requires-Dist: pandas
Requires-Dist: rdkit>2023.09.1
Requires-Dist: scikit-learn
